p3dpkg/__init__.py
p3dpkg/p3dBlob.py
p3dpkg/p3dBlobPy.py
p3dpkg/p3dFilt.py
p3dpkg/p3dFiltPy.py
p3dpkg/p3dSITKPy.py
p3dpkg/p3dSkel.py
p3dpkg/p3dSkelPy.py
p3dpkg/p3d_SITK_common_lib.py
p3dpkg/p3d_SITK_read_raw.py
p3dpkg/p3d_common_lib.py
p3dpkg_bckup/__init__.py
p3dpkg_bckup/p3dBlob.py
p3dpkg_bckup/p3dBlobPy.py
p3dpkg_bckup/p3dFilt.py
p3dpkg_bckup/p3dFiltPy.py
p3dpkg_bckup/p3dSITKPy.py
p3dpkg_bckup/p3dSkel.py
p3dpkg_bckup/p3dSkelPy.py
p3dpkg_bckup/p3d_SITK_common_lib.py
p3dpkg_bckup/p3d_SITK_read_raw.py
p3dpkg_bckup/p3d_common_lib.py
p3dpkg-0.0.5.dist-info/LICENSE
p3dpkg-0.0.5.dist-info/METADATA
p3dpkg-0.0.5.dist-info/WHEEL
p3dpkg-0.0.5.dist-info/top_level.txt
p3dpkg-0.0.5.dist-info/RECORD
