Metadata-Version: 2.1
Name: p3dpkg
Version: 0.0.5
Summary: Pore3d with python wrappers
Home-page: https://gitlab.elettra.eu/amal.abouelhassan/pore3d_py
Author: Amal Aboulhassan
Author-email: aboulhassan.amal@gmail.com
License: UNKNOWN
Project-URL: Bug Tracker, https://gitlab.elettra.eu/amal.abouelhassan/pore3d_py/-/issues
Platform: UNKNOWN
Classifier: Programming Language :: Python :: 3
Classifier: License :: OSI Approved :: MIT License
Classifier: Operating System :: OS Independent
Requires-Python: >=3.6
License-File: LICENSE
